testverse/__init__.py
testverse/cli.py
testverse/connector.py
testverse/evaluator.py
testverse-0.0.14.dist-info/LICENSE
testverse-0.0.14.dist-info/METADATA
testverse-0.0.14.dist-info/WHEEL
testverse-0.0.14.dist-info/RECORD
